LDVisualization/__init__.py
LDVisualization/const.py
LDVisualization/inputHandlers.py
LDVisualization/utils.py
LDVisualization/visualize.py
ldvisualization-0.0.3.dist-info/METADATA
ldvisualization-0.0.3.dist-info/WHEEL
ldvisualization-0.0.3.dist-info/licenses/LICENSE
ldvisualization-0.0.3.dist-info/RECORD
